ConfigFilesManager/__init__.py
ConfigFilesManager/configFilesManager.py
ConfigFilesManager-0.1b1.dist-info/METADATA
ConfigFilesManager-0.1b1.dist-info/RECORD
ConfigFilesManager-0.1b1.dist-info/WHEEL
ConfigFilesManager-0.1b1.dist-info/top_level.txt
