Metadata-Version: 2.1
Name: ConfigFilesManager
Version: 0.1b1
Summary: A python module to a easy manage configs files for applications
Home-page: https://github.com/orgs/PyModuleManage
Author: eamanu
Author-email: eamanu@eamanu.com
License: GPL-v3+
Project-URL: Source, https://github.com/PyModuleManage/ConfigFilesManager
Project-URL: Bug Reports, https://github.com/PyModuleManage/ConfigFilesManager/issues
Platform: UNKNOWN
Classifier: Development Status :: 4 - Beta
Classifier: Intended Audience :: Developers
Classifier: Topic :: Software Development :: Build Tools
Classifier: License :: OSI Approved :: GNU General Public License v3 or later (GPLv3+)
Classifier: Programming Language :: Python :: 3
